colorise/__init__.py
colorise/attributes.py
colorise/cluts.py
colorise/color_tools.py
colorise/error.py
colorise/formatter.py
colorise/terminal.py
colorise/nix/__init__.py
colorise/nix/cluts.py
colorise/nix/color_functions.py
colorise/win/__init__.py
colorise/win/cluts.py
colorise/win/color_functions.py
colorise/win/win32_functions.py
colorise/win/winhandle.py
colorise-1.0.1.dist-info/LICENSE
colorise-1.0.1.dist-info/METADATA
colorise-1.0.1.dist-info/WHEEL
colorise-1.0.1.dist-info/top_level.txt
colorise-1.0.1.dist-info/RECORD
