Metadata-Version: 2.1
Name: colorise
Version: 1.0.1
Summary: Easily print colored text to the console
Home-page: https://github.com/MisanthropicBit/colorise
Author: Alexander Asp Bock
Author-email: albo.developer@gmail.com
License: BSD 3-Clause License
Project-URL: Issue Tracker, https://github.com/MisanthropicBit/colorise/issues
Project-URL: Documentation, https://colorise.readthedocs.io/en/latest/
Keywords: text,color,colorise,colorize,console,terminal
Platform: Platform independent
Classifier: Development Status :: 5 - Production/Stable
Classifier: Intended Audience :: Developers
Classifier: Topic :: Utilities
Classifier: Topic :: Terminals
Classifier: License :: OSI Approved :: BSD License
Classifier: Programming Language :: Python :: 3.4
Classifier: Programming Language :: Python :: 3.5
Classifier: Programming Language :: Python :: 3.6
Classifier: Programming Language :: Python :: 3.7
Classifier: Programming Language :: Python :: Implementation :: PyPy
Requires-Python: >=3.4
